{
  "schemaVersion": "1.0.0",
  "rulePackId": "smnyl-new-professional-2026",
  "sourceDocument": "CC 2026 Asesores Nuevos Profesionales",
  "effectiveFrom": "2026-01-01",
  "effectiveTo": "2026-12-31",
  "currency": "MXN",
  "participantType": "new_professional_advisor",
  "payoutTruth": false,
  "payoutTruthRule": "commission_statement_required",
  "sourceEvidence": [
    "CC 2026 Asesores Nuevos Profesionales.pdf"
  ],
  "globalExclusions": {
    "personalPoliciesExcluded": true,
    "legalEntitiesExcluded": true,
    "onlyDefinitiveKeys": true,
    "activeAdvisorsOnly": true,
    "payrollDiscountExcluded": true,
    "aveExcluded": true,
    "additionalUniversalProductContributionsExcluded": true,
    "gmmiInitialPremiumsCommissionsExcludedForInsuredAge60Plus": true,
    "paidAppliedAtCloseRequired": true,
    "canceledPoliciesMayBeDeductedRecalculated": true,
    "personasMoralesExcluded": {
      "enabled": true,
      "label": "No participan claves de Asesores que sean Personas Morales.",
      "source": "CC 2026 Asesores Nuevos Profesionales - Bases"
    }
  },
  "concepts": {
    "life-initial-bonus": {
      "displayName": "Bono Inicial Vida",
      "category": "life",
      "cadence": "initial",
      "payoutTruth": false,
      "payoutTruthRule": "commission_statement_required",
      "sourceEvidence": [
        "CC 2026 Asesores Nuevos Profesionales.pdf"
      ],
      "modelStatus": "implemented_candidate",
      "targetPremiumGroupsTable": {
        "unit": "MXN",
        "semesterMonths": [
          1,
          2,
          3,
          4,
          5,
          6
        ],
        "groups": {
          "1": [455000, 910000, 1370000, 1825000, 2280000, 2735000],
          "2": [420000, 835000, 1255000, 1670000, 2090000, 2505000],
          "3": [355000, 710000, 1065000, 1420000, 1775000, 2125000],
          "4": [325000, 645000, 970000, 1290000, 1615000, 1945000],
          "5": [300000, 605000, 905000, 1215000, 1515000, 1820000],
          "6": [275000, 560000, 835000, 1115000, 1400000, 1675000],
          "7": [250000, 500000, 745000, 1000000, 1245000, 1495000],
          "8": [210000, 430000, 640000, 860000, 1075000, 1290000],
          "9": [185000, 375000, 555000, 740000, 930000, 1115000],
          "10": [160000, 315000, 475000, 640000, 790000, 950000],
          "11": [125000, 245000, 370000, 490000, 615000, 735000],
          "12": [85000, 175000, 260000, 350000, 440000, 525000],
          "13": [75000, 140000, 215000, 280000, 355000, 420000],
          "14": [60000, 130000, 190000, 260000, 320000, 385000],
          "15": [55000, 110000, 160000, 220000, 275000, 330000],
          "16": [50000, 90000, 135000, 185000, 225000, 275000]
        }
      },
      "policyGoalsTable": {
        "monthlyLifePolicyGoalBySemesterMonth": {
          "1": 1,
          "2": 1,
          "3": 1,
          "4": 1,
          "5": 1,
          "6": null
        },
        "semesterAccumulatedPolicyGoals": {
          "1": 2.5,
          "2": 5,
          "3": 7.5,
          "4": 10,
          "5": 12.5,
          "6": 15
        },
        "annualPolicyGoalsSecondSemesterOnly": {
          "1": 17.5,
          "2": 20,
          "3": 22.5,
          "4": 25,
          "5": 27.5,
          "6": 30
        }
      },
      "minimumLimraByTenureTable": [
        {
          "fromMonth": 1,
          "toMonth": 24,
          "minimumLimra": 75.5
        },
        {
          "fromMonth": 25,
          "toMonth": 36,
          "minimumLimra": 80.5
        },
        {
          "fromMonth": 37,
          "toMonth": null,
          "minimumLimra": 84.5
        }
      ],
      "bonusRateByGroupAndLimraTable": {
        "1": { "minimumIndex": 0.098, "87.5": 0.195, "89.5": 0.33, "91.5": 0.36, "95.5": 0.45 },
        "2": { "minimumIndex": 0.083, "87.5": 0.165, "89.5": 0.305, "91.5": 0.34, "95.5": 0.43 },
        "3": { "minimumIndex": 0.07, "87.5": 0.14, "89.5": 0.275, "91.5": 0.32, "95.5": 0.4 },
        "4": { "minimumIndex": 0.063, "87.5": 0.125, "89.5": 0.265, "91.5": 0.3, "95.5": 0.37 },
        "5": { "minimumIndex": 0.058, "87.5": 0.115, "89.5": 0.245, "91.5": 0.28, "95.5": 0.35 },
        "6": { "minimumIndex": 0.053, "87.5": 0.105, "89.5": 0.22, "91.5": 0.26, "95.5": 0.33 },
        "7": { "minimumIndex": 0.05, "87.5": 0.1, "89.5": 0.195, "91.5": 0.25, "95.5": 0.31 },
        "8": { "minimumIndex": 0.048, "87.5": 0.095, "89.5": 0.165, "91.5": 0.23, "95.5": 0.29 },
        "9": { "minimumIndex": 0.045, "87.5": 0.09, "89.5": 0.14, "91.5": 0.22, "95.5": 0.27 },
        "10": { "minimumIndex": 0.043, "87.5": 0.085, "89.5": 0.11, "91.5": 0.2, "95.5": 0.25 },
        "11": { "minimumIndex": 0.04, "87.5": 0.08, "89.5": 0.1, "91.5": 0.18, "95.5": 0.23 },
        "12": { "minimumIndex": 0.035, "87.5": 0.07, "89.5": 0.09, "91.5": 0.17, "95.5": 0.21 },
        "13": { "minimumIndex": 0.028, "87.5": 0.055, "89.5": 0.08, "91.5": 0.15, "95.5": 0.19 },
        "14": { "minimumIndex": 0.023, "87.5": 0.045, "89.5": 0.07, "91.5": 0.14, "95.5": 0.17 },
        "15": { "minimumIndex": 0.018, "87.5": 0.035, "89.5": 0.055, "91.5": 0.12, "95.5": 0.15 },
        "16": { "minimumIndex": 0.01, "87.5": 0.02, "89.5": 0.025, "91.5": 0.11, "95.5": 0.14 }
      },
      "contestMonth13To36MinimumRateFloor": {
        "enabled": true,
        "fromMonth": 13,
        "toMonth": 36,
        "minimumRate": 0.098,
        "appliesOnlyWhenGroupPolicyGoalsAndMinimumLimraAreMet": true
      },
      "monthlyAdvanceGroupCapRule": {
        "firstSemesterInNewProfessionalBook": "use_current_calculated_group",
        "otherwise": "cap_by_previous_semester_closing_group",
        "missingOrWorseThanGroup13CapGroup": 13,
        "lowerGroupNumberIsBetter": true,
        "effectiveMonthlyAdvanceGroupStrategy": "worse_of_current_group_and_cap_group",
        "semesterSettlementGroupStrategy": "use_actual_current_group"
      }
    },
    "life-renewal-bonus": {
      "displayName": "Bono de Renovacion Vida",
      "category": "life",
      "cadence": "renewal",
      "payoutTruth": false,
      "payoutTruthRule": "commission_statement_required",
      "sourceEvidence": [
        "CC 2026 Asesores Nuevos Profesionales.pdf"
      ],
      "modelStatus": "implemented_candidate",
      "igcTierMetadata": {
        "minimumIgc": 91,
        "tierColumns": [
          91,
          92.5,
          95,
          95.75
        ],
        "tierResolution": [
          {
            "minimumIgc": 95.75,
            "tier": "95.75"
          },
          {
            "minimumIgc": 95,
            "tier": "95"
          },
          {
            "minimumIgc": 92.5,
            "tier": "92.5"
          },
          {
            "minimumIgc": 91,
            "tier": "91"
          }
        ],
        "belowMinimumStatus": "ineligible_igc_goal_not_met"
      },
      "bonusRateByGroupAndIgcTable": {
        "1": { "91": 0.06, "92.5": 0.08, "95": 0.11, "95.75": 0.16 },
        "2": { "91": 0.055, "92.5": 0.07, "95": 0.095, "95.75": 0.14 },
        "3": { "91": 0.05, "92.5": 0.065, "95": 0.09, "95.75": 0.13 },
        "4": { "91": 0.046, "92.5": 0.06, "95": 0.085, "95.75": 0.12 },
        "5": { "91": 0.043, "92.5": 0.055, "95": 0.08, "95.75": 0.11 },
        "6": { "91": 0.04, "92.5": 0.05, "95": 0.07, "95.75": 0.1 },
        "7": { "91": 0.037, "92.5": 0.048, "95": 0.065, "95.75": 0.095 },
        "8": { "91": 0.034, "92.5": 0.044, "95": 0.06, "95.75": 0.09 },
        "9": { "91": 0.03, "92.5": 0.04, "95": 0.055, "95.75": 0.08 },
        "10": { "91": 0.028, "92.5": 0.036, "95": 0.05, "95.75": 0.07 },
        "11": { "91": 0.025, "92.5": 0.032, "95": 0.045, "95.75": 0.06 },
        "12": { "91": 0.022, "92.5": 0.028, "95": 0.04, "95.75": 0.05 },
        "13": { "91": 0.019, "92.5": 0.024, "95": 0.03, "95.75": 0.04 },
        "14": { "91": 0.015, "92.5": 0.02, "95": 0.025, "95.75": 0.03 },
        "15": { "91": 0.013, "92.5": 0.016, "95": 0.02, "95.75": 0.025 },
        "16": { "91": 0.01, "92.5": 0.012, "95": 0.013, "95.75": 0.015 }
      }
    },
    "gmmi-initial-premium-bonus": {
      "displayName": "GMMI Bono Primas Iniciales",
      "category": "gmmi",
      "cadence": "initial",
      "payoutTruth": false,
      "payoutTruthRule": "commission_statement_required",
      "sourceEvidence": [
        "CC 2026 Asesores Nuevos Profesionales.pdf"
      ],
      "modelStatus": "implemented_candidate",
      "gmmiInitialPremiumQuarterlyBonusTable": {
        "sourceTable": "Table 7. Prima neta pagada y polizas iniciales de GMMI en el trimestre.",
        "unit": "MXN",
        "premiumGoalBasis": "accumulated_eligible_paid_gmmi_initial_net_premium",
        "policyGoalBasis": "accumulated_gmmi_initial_policies_paid",
        "quarterMonths": [
          1,
          2,
          3
        ],
        "groups": {
          "1": {
            "group": 1,
            "month1PremiumGoal": 315000,
            "month2PremiumGoal": 640000,
            "month3PremiumGoal": 790000,
            "policyGoal": 8,
            "bonusRate": 0.16
          },
          "2": {
            "group": 2,
            "month1PremiumGoal": 245000,
            "month2PremiumGoal": 485000,
            "month3PremiumGoal": 610000,
            "policyGoal": 6,
            "bonusRate": 0.14
          },
          "3": {
            "group": 3,
            "month1PremiumGoal": 195000,
            "month2PremiumGoal": 390000,
            "month3PremiumGoal": 485000,
            "policyGoal": 5,
            "bonusRate": 0.13
          },
          "4": {
            "group": 4,
            "month1PremiumGoal": 135000,
            "month2PremiumGoal": 285000,
            "month3PremiumGoal": 365000,
            "policyGoal": 4,
            "bonusRate": 0.1
          },
          "5": {
            "group": 5,
            "month1PremiumGoal": 115000,
            "month2PremiumGoal": 225000,
            "month3PremiumGoal": 280000,
            "policyGoal": 3,
            "bonusRate": 0.09
          },
          "6": {
            "group": 6,
            "month1PremiumGoal": 80000,
            "month2PremiumGoal": 170000,
            "month3PremiumGoal": 215000,
            "policyGoal": 3,
            "bonusRate": 0.08
          },
          "7": {
            "group": 7,
            "month1PremiumGoal": 65000,
            "month2PremiumGoal": 125000,
            "month3PremiumGoal": 160000,
            "policyGoal": 2,
            "bonusRate": 0.07
          }
        }
      }
    },
    "gmmi-initial-premium-growth-annual-bonus": {
      "displayName": "GMMI Bono Anual por Crecimiento de Primas Iniciales",
      "category": "gmmi",
      "cadence": "annual",
      "payoutTruth": false,
      "payoutTruthRule": "commission_statement_required",
      "sourceEvidence": [
        "CC 2026 Asesores Nuevos Profesionales.pdf"
      ],
      "modelStatus": "implemented_candidate",
      "gmmiInitialPremiumGrowthAnnualBonusTable": {
        "sourceTable": "Table 8. Bono Anual por Crecimiento de Primas Iniciales.",
        "bonusBase": "annual_gmmi_initial_premium_monthly_bonus_base",
        "growthRateFormula": "(currentContestYearEligibleGmmiInitialNetPremium - previousContestYearEligibleGmmiInitialNetPremium) / previousContestYearEligibleGmmiInitialNetPremium",
        "tiers": [
          {
            "tier": 1,
            "minimumGrowthRate": 0.15,
            "maximumGrowthRateExclusive": 0.2,
            "bonusRate": 0.1
          },
          {
            "tier": 2,
            "minimumGrowthRate": 0.2,
            "maximumGrowthRateExclusive": 0.3,
            "bonusRate": 0.2
          },
          {
            "tier": 3,
            "minimumGrowthRate": 0.3,
            "maximumGrowthRateExclusive": null,
            "bonusRate": 0.3
          }
        ]
      }
    },
    "gmmi-renewal-premium-bonus": {
      "displayName": "Bono Prima de Renovacion GMMI",
      "category": "gmmi",
      "cadence": "renewal",
      "payoutTruth": false,
      "payoutTruthRule": "commission_statement_required",
      "sourceEvidence": [
        "CC 2026 Asesores Nuevos Profesionales.pdf"
      ],
      "modelStatus": "skeleton_not_calculated"
    },
    "gmmi-loss-ratio-annual-bonus": {
      "displayName": "Bono Anual Siniestralidad GMMI",
      "category": "gmmi",
      "cadence": "annual",
      "payoutTruth": false,
      "payoutTruthRule": "commission_statement_required",
      "sourceEvidence": [
        "CC 2026 Asesores Nuevos Profesionales.pdf"
      ],
      "modelStatus": "skeleton_not_calculated"
    },
    "connection-bonus": {
      "displayName": "Bono de Conexion",
      "category": "relationship",
      "cadence": "event_and_monthly",
      "payoutTruth": false,
      "payoutTruthRule": "commission_statement_required",
      "sourceEvidence": [
        "CC 2026 Asesores Nuevos Profesionales.pdf"
      ],
      "modelStatus": "skeleton_not_calculated"
    },
    "development-bonus": {
      "displayName": "Bono de Desarrollo",
      "category": "relationship",
      "cadence": "monthly",
      "payoutTruth": false,
      "payoutTruthRule": "commission_statement_required",
      "sourceEvidence": [
        "CC 2026 Asesores Nuevos Profesionales.pdf"
      ],
      "modelStatus": "skeleton_not_calculated"
    },
    "temporary-total-disability-benefit": {
      "displayName": "Beneficio por Invalidez Total Temporal",
      "category": "benefit",
      "cadence": "event",
      "payoutTruth": false,
      "payoutTruthRule": "commission_statement_required",
      "sourceEvidence": [
        "CC 2026 Asesores Nuevos Profesionales.pdf"
      ],
      "modelStatus": "skeleton_not_calculated"
    },
    "death-benefit": {
      "displayName": "Beneficio por Fallecimiento",
      "category": "benefit",
      "cadence": "event",
      "payoutTruth": false,
      "payoutTruthRule": "commission_statement_required",
      "sourceEvidence": [
        "CC 2026 Asesores Nuevos Profesionales.pdf"
      ],
      "modelStatus": "skeleton_not_calculated"
    }
  }
}
